texttab/__init__.py
texttab/const.py
texttab/fields.py
texttab/formatters.py
texttab/table.py
texttab-0.5.4.dist-info/LICENSE.txt
texttab-0.5.4.dist-info/METADATA
texttab-0.5.4.dist-info/WHEEL
texttab-0.5.4.dist-info/top_level.txt
texttab-0.5.4.dist-info/RECORD
